ameriopt/___init__.py
ameriopt/gbm.py
ameriopt/helper.py
ameriopt/lsm_policy.py
ameriopt/rl_policy.py
ameriopt-0.1.5.dist-info/LICENSE
ameriopt-0.1.5.dist-info/METADATA
ameriopt-0.1.5.dist-info/WHEEL
ameriopt-0.1.5.dist-info/RECORD
